{
    "collection": "Pwnkey",
    "id": 5967,
    "assets": [
        "Black night.png",
        "Light green eyes .png",
        "Zombie.png",
        "Hilarious laughing .png",
        "Ears bow.png",
        "Hidden hair.png",
        "Capitain.png",
        "Blue glasses.png"
    ],
    "creation_time": "2024-04-11 23:37:49",
    "story": "Pwnky, a creature from the Black night of Inpinity Online, ventured through the digital realms with Light green eyes  eyes that sparkled with curiosity, a Zombie body that shimmered with the essence of creativity, and a Hilarious laughing  mouth that resonated with the voices of countless creators. On this journey, Pwnky's Ears bow ears fluttered in the electronic winds, and Hidden hair hair flowed like the rivers of code that shaped the landscape. Adorned with a Capitain hat crafted by the artisans of the net, Pwnky discovered the Blue glasses, a relic that could unlock new realms in this infinite universe.",
    "dimensions": "370x370",
    "hash": "5967_2024-04-11_233749",
    "description": "a new Pwnkey with Black night, Light green eyes , Zombie, Hilarious laughing , Ears bow, Hidden hair, Capitain, Blue glasses",
    "rarity_percentages": {
        "Black night.png": "5.81%",
        "Light green eyes .png": "7.63%",
        "Zombie.png": "19.45%",
        "Hilarious laughing .png": "13.52%",
        "Ears bow.png": "14.11%",
        "Hidden hair.png": "7.44%",
        "Capitain.png": "12.01%",
        "Blue glasses.png": "13.83%"
    },
    "rarity": "Normal"
}