{
    "collection": "Pwnkey",
    "id": 572,
    "assets": [
        "Green.png",
        "Dreaming eyes.png",
        "Zombie.png",
        "Hilarious laughing .png",
        "Golden ears.png",
        "Hidden hair.png",
        "Vikings hat.png",
        "Blue sunglasses .png"
    ],
    "creation_time": "2024-04-11 23:29:54",
    "story": "Pwnky, a creature from the Green of Inpinity Online, ventured through the digital realms with Dreaming eyes eyes that sparkled with curiosity, a Zombie body that shimmered with the essence of creativity, and a Hilarious laughing  mouth that resonated with the voices of countless creators. On this journey, Pwnky's Golden ears ears fluttered in the electronic winds, and Hidden hair hair flowed like the rivers of code that shaped the landscape. Adorned with a Vikings hat hat crafted by the artisans of the net, Pwnky discovered the Blue sunglasses , a relic that could unlock new realms in this infinite universe.",
    "dimensions": "370x370",
    "hash": "572_2024-04-11_232954",
    "description": "a new Pwnkey with Green, Dreaming eyes, Zombie, Hilarious laughing , Golden ears, Hidden hair, Vikings hat, Blue sunglasses ",
    "rarity_percentages": {
        "Green.png": "6.29%",
        "Dreaming eyes.png": "7.41%",
        "Zombie.png": "19.45%",
        "Hilarious laughing .png": "13.52%",
        "Golden ears.png": "14.61%",
        "Hidden hair.png": "7.44%",
        "Vikings hat.png": "12.58%",
        "Blue sunglasses .png": "14.62%"
    },
    "rarity": "Rare"
}