{
    "collection": "Pwnkey",
    "id": 5330,
    "assets": [
        "City.png",
        "Golden hair.png",
        "Sick.png",
        "Shocked open mouth .png",
        "Golden ears.png",
        "Dark brown hair.png",
        "Vikings hat.png",
        "Horns.png"
    ],
    "creation_time": "2024-04-11 23:36:50",
    "story": "Pwnky, a creature from the City of Inpinity Online, ventured through the digital realms with Golden hair eyes that sparkled with curiosity, a Sick body that shimmered with the essence of creativity, and a Shocked open mouth  mouth that resonated with the voices of countless creators. On this journey, Pwnky's Golden ears ears fluttered in the electronic winds, and Dark brown hair hair flowed like the rivers of code that shaped the landscape. Adorned with a Vikings hat hat crafted by the artisans of the net, Pwnky discovered the Horns, a relic that could unlock new realms in this infinite universe.",
    "dimensions": "370x370",
    "hash": "5330_2024-04-11_233650",
    "description": "a new Pwnkey with City, Golden hair, Sick, Shocked open mouth , Golden ears, Dark brown hair, Vikings hat, Horns",
    "rarity_percentages": {
        "City.png": "6.44%",
        "Golden hair.png": "14.62%",
        "Sick.png": "20.73%",
        "Shocked open mouth .png": "13.88%",
        "Golden ears.png": "14.61%",
        "Dark brown hair.png": "6.99%",
        "Vikings hat.png": "12.58%",
        "Horns.png": "14.20%"
    },
    "rarity": "Rare"
}