{
    "collection": "Pwnkey",
    "id": 5153,
    "assets": [
        "Landscape .png",
        "Dark bad eyes.png",
        "Mechanic body.png",
        "Shocked open mouth .png",
        "Colored ears.png",
        "Dark brown hair.png",
        "Astronaut suite .png",
        "Halo.png"
    ],
    "creation_time": "2024-04-11 23:36:34",
    "story": "Pwnky, a creature from the Landscape  of Inpinity Online, ventured through the digital realms with Dark bad eyes eyes that sparkled with curiosity, a Mechanic body body that shimmered with the essence of creativity, and a Shocked open mouth  mouth that resonated with the voices of countless creators. On this journey, Pwnky's Colored ears ears fluttered in the electronic winds, and Dark brown hair hair flowed like the rivers of code that shaped the landscape. Adorned with a Astronaut suite  hat crafted by the artisans of the net, Pwnky discovered the Halo, a relic that could unlock new realms in this infinite universe.",
    "dimensions": "370x370",
    "hash": "5153_2024-04-11_233634",
    "description": "a new Pwnkey with Landscape , Dark bad eyes, Mechanic body, Shocked open mouth , Colored ears, Dark brown hair, Astronaut suite , Halo",
    "rarity_percentages": {
        "Landscape .png": "6.27%",
        "Dark bad eyes.png": "7.42%",
        "Mechanic body.png": "19.40%",
        "Shocked open mouth .png": "13.88%",
        "Colored ears.png": "14.78%",
        "Dark brown hair.png": "6.99%",
        "Astronaut suite .png": "12.23%",
        "Halo.png": "15.19%"
    },
    "rarity": "Normal"
}