{
    "collection": "Pwnkey",
    "id": 1430,
    "assets": [
        "Green.png",
        "Bad eyes.png",
        "Sick.png",
        "Hilarious laughing .png",
        "Ears bow.png",
        "Blue heroic hair.png",
        "Comic crown.png",
        "sunglasses beach.png"
    ],
    "creation_time": "2024-04-11 23:31:05",
    "story": "Pwnky, a creature from the Green of Inpinity Online, ventured through the digital realms with Bad eyes eyes that sparkled with curiosity, a Sick body that shimmered with the essence of creativity, and a Hilarious laughing  mouth that resonated with the voices of countless creators. On this journey, Pwnky's Ears bow ears fluttered in the electronic winds, and Blue heroic hair hair flowed like the rivers of code that shaped the landscape. Adorned with a Comic crown hat crafted by the artisans of the net, Pwnky discovered the sunglasses beach, a relic that could unlock new realms in this infinite universe.",
    "dimensions": "370x370",
    "hash": "1430_2024-04-11_233105",
    "description": "a new Pwnkey with Green, Bad eyes, Sick, Hilarious laughing , Ears bow, Blue heroic hair, Comic crown, sunglasses beach",
    "rarity_percentages": {
        "Green.png": "6.29%",
        "Bad eyes.png": "7.16%",
        "Sick.png": "20.73%",
        "Hilarious laughing .png": "13.52%",
        "Ears bow.png": "14.11%",
        "Blue heroic hair.png": "7.51%",
        "Comic crown.png": "13.09%",
        "sunglasses beach.png": "13.93%"
    },
    "rarity": "Rare"
}