{
    "collection": "Pwnkey",
    "id": 5647,
    "assets": [
        "Red .png",
        "Eyes of love.png",
        "Sick.png",
        "Hilarious laughing .png",
        "Ears bow.png",
        "Golden hair.png",
        "Crown.png",
        "Halo.png"
    ],
    "creation_time": "2024-04-11 23:37:20",
    "story": "Pwnky, a creature from the Red  of Inpinity Online, ventured through the digital realms with Eyes of love eyes that sparkled with curiosity, a Sick body that shimmered with the essence of creativity, and a Hilarious laughing  mouth that resonated with the voices of countless creators. On this journey, Pwnky's Ears bow ears fluttered in the electronic winds, and Golden hair hair flowed like the rivers of code that shaped the landscape. Adorned with a Crown hat crafted by the artisans of the net, Pwnky discovered the Halo, a relic that could unlock new realms in this infinite universe.",
    "dimensions": "370x370",
    "hash": "5647_2024-04-11_233720",
    "description": "a new Pwnkey with Red , Eyes of love, Sick, Hilarious laughing , Ears bow, Golden hair, Crown, Halo",
    "rarity_percentages": {
        "Red .png": "5.99%",
        "Eyes of love.png": "6.83%",
        "Sick.png": "20.73%",
        "Hilarious laughing .png": "13.52%",
        "Ears bow.png": "14.11%",
        "Golden hair.png": "14.62%",
        "Crown.png": "12.51%",
        "Halo.png": "15.19%"
    },
    "rarity": "Common"
}