{
    "collection": "Pwnkey",
    "id": 992,
    "assets": [
        "Red .png",
        "Pink eyes.png",
        "Zombie.png",
        "Smiling .png",
        "Gold earrings .png",
        "Hair on fire.png",
        "Vikings hat.png",
        "Halo.png"
    ],
    "creation_time": "2024-04-11 23:30:28",
    "story": "Pwnky, a creature from the Red  of Inpinity Online, ventured through the digital realms with Pink eyes eyes that sparkled with curiosity, a Zombie body that shimmered with the essence of creativity, and a Smiling  mouth that resonated with the voices of countless creators. On this journey, Pwnky's Gold earrings  ears fluttered in the electronic winds, and Hair on fire hair flowed like the rivers of code that shaped the landscape. Adorned with a Vikings hat hat crafted by the artisans of the net, Pwnky discovered the Halo, a relic that could unlock new realms in this infinite universe.",
    "dimensions": "370x370",
    "hash": "992_2024-04-11_233028",
    "description": "a new Pwnkey with Red , Pink eyes, Zombie, Smiling , Gold earrings , Hair on fire, Vikings hat, Halo",
    "rarity_percentages": {
        "Red .png": "5.99%",
        "Pink eyes.png": "7.11%",
        "Zombie.png": "19.45%",
        "Smiling .png": "14.37%",
        "Gold earrings .png": "13.97%",
        "Hair on fire.png": "7.30%",
        "Vikings hat.png": "12.58%",
        "Halo.png": "15.19%"
    },
    "rarity": "Normal"
}