{
    "collection": "Pwnkey",
    "id": 438,
    "assets": [
        "Yellow.png",
        "Red eyes.png",
        "Zombie.png",
        "Sad.png",
        "Comic ear.png",
        "Dark brown hair.png",
        "Black hat.png",
        "Jacket .png"
    ],
    "creation_time": "2024-04-11 23:29:43",
    "story": "Pwnky, a creature from the Yellow of Inpinity Online, ventured through the digital realms with Red eyes eyes that sparkled with curiosity, a Zombie body that shimmered with the essence of creativity, and a Sad mouth that resonated with the voices of countless creators. On this journey, Pwnky's Comic ear ears fluttered in the electronic winds, and Dark brown hair hair flowed like the rivers of code that shaped the landscape. Adorned with a Black hat hat crafted by the artisans of the net, Pwnky discovered the Jacket , a relic that could unlock new realms in this infinite universe.",
    "dimensions": "370x370",
    "hash": "438_2024-04-11_232943",
    "description": "a new Pwnkey with Yellow, Red eyes, Zombie, Sad, Comic ear, Dark brown hair, Black hat, Jacket ",
    "rarity_percentages": {
        "Yellow.png": "6.45%",
        "Red eyes.png": "7.24%",
        "Zombie.png": "19.45%",
        "Sad.png": "14.55%",
        "Comic ear.png": "14.02%",
        "Dark brown hair.png": "6.99%",
        "Black hat.png": "12.77%",
        "Jacket .png": "14.68%"
    },
    "rarity": "Common"
}