{
    "collection": "Pwnkey",
    "id": 1586,
    "assets": [
        "Yellow Clouds.png",
        "Eyes of love.png",
        "Zombie.png",
        "Smiling .png",
        "Ears bow.png",
        "Brown hair.png",
        "Astronaut suite .png",
        "Horns.png"
    ],
    "creation_time": "2024-04-11 23:31:18",
    "story": "Pwnky, a creature from the Yellow Clouds of Inpinity Online, ventured through the digital realms with Eyes of love eyes that sparkled with curiosity, a Zombie body that shimmered with the essence of creativity, and a Smiling  mouth that resonated with the voices of countless creators. On this journey, Pwnky's Ears bow ears fluttered in the electronic winds, and Brown hair hair flowed like the rivers of code that shaped the landscape. Adorned with a Astronaut suite  hat crafted by the artisans of the net, Pwnky discovered the Horns, a relic that could unlock new realms in this infinite universe.",
    "dimensions": "370x370",
    "hash": "1586_2024-04-11_233118",
    "description": "a new Pwnkey with Yellow Clouds, Eyes of love, Zombie, Smiling , Ears bow, Brown hair, Astronaut suite , Horns",
    "rarity_percentages": {
        "Yellow Clouds.png": "6.11%",
        "Eyes of love.png": "6.83%",
        "Zombie.png": "19.45%",
        "Smiling .png": "14.37%",
        "Ears bow.png": "14.11%",
        "Brown hair.png": "7.04%",
        "Astronaut suite .png": "12.23%",
        "Horns.png": "14.20%"
    },
    "rarity": "Rare"
}