{
    "collection": "Pwnkey",
    "id": 5644,
    "assets": [
        "Black night.png",
        "Red eyes.png",
        "Body.png",
        "Smiling .png",
        "Gold earrings .png",
        "Blue heroic hair.png",
        "Comic crown.png",
        "Jacket .png"
    ],
    "creation_time": "2024-04-11 23:37:19",
    "story": "Pwnky, a creature from the Black night of Inpinity Online, ventured through the digital realms with Red eyes eyes that sparkled with curiosity, a Body body that shimmered with the essence of creativity, and a Smiling  mouth that resonated with the voices of countless creators. On this journey, Pwnky's Gold earrings  ears fluttered in the electronic winds, and Blue heroic hair hair flowed like the rivers of code that shaped the landscape. Adorned with a Comic crown hat crafted by the artisans of the net, Pwnky discovered the Jacket , a relic that could unlock new realms in this infinite universe.",
    "dimensions": "370x370",
    "hash": "5644_2024-04-11_233719",
    "description": "a new Pwnkey with Black night, Red eyes, Body, Smiling , Gold earrings , Blue heroic hair, Comic crown, Jacket ",
    "rarity_percentages": {
        "Black night.png": "5.81%",
        "Red eyes.png": "7.24%",
        "Body.png": "20.28%",
        "Smiling .png": "14.37%",
        "Gold earrings .png": "13.97%",
        "Blue heroic hair.png": "7.51%",
        "Comic crown.png": "13.09%",
        "Jacket .png": "14.68%"
    },
    "rarity": "Normal"
}