{
    "collection": "Pwnkey",
    "id": 3308,
    "assets": [
        "Purple night.png",
        "Brown eyes .png",
        "Golden body.png",
        "Shocked open mouth .png",
        "Golden ears.png",
        "Hidden hair.png",
        "Black hat.png",
        "Horns.png"
    ],
    "creation_time": "2024-04-11 23:33:47",
    "story": "Pwnky, a creature from the Purple night of Inpinity Online, ventured through the digital realms with Brown eyes  eyes that sparkled with curiosity, a Golden body body that shimmered with the essence of creativity, and a Shocked open mouth  mouth that resonated with the voices of countless creators. On this journey, Pwnky's Golden ears ears fluttered in the electronic winds, and Hidden hair hair flowed like the rivers of code that shaped the landscape. Adorned with a Black hat hat crafted by the artisans of the net, Pwnky discovered the Horns, a relic that could unlock new realms in this infinite universe.",
    "dimensions": "370x370",
    "hash": "3308_2024-04-11_233347",
    "description": "a new Pwnkey with Purple night, Brown eyes , Golden body, Shocked open mouth , Golden ears, Hidden hair, Black hat, Horns",
    "rarity_percentages": {
        "Purple night.png": "6.31%",
        "Brown eyes .png": "6.95%",
        "Golden body.png": "20.32%",
        "Shocked open mouth .png": "13.88%",
        "Golden ears.png": "14.61%",
        "Hidden hair.png": "7.44%",
        "Black hat.png": "12.77%",
        "Horns.png": "14.20%"
    },
    "rarity": "Normal"
}