{
    "collection": "Pwnkey",
    "id": 4474,
    "assets": [
        "Cyan.png",
        "Blue eyes .png",
        "Zombie.png",
        "Shocked open mouth .png",
        "Comic ear.png",
        "Cool blue hair.png",
        "Black hat.png",
        "Horns.png"
    ],
    "creation_time": "2024-04-11 23:35:32",
    "story": "Pwnky, a creature from the Cyan of Inpinity Online, ventured through the digital realms with Blue eyes  eyes that sparkled with curiosity, a Zombie body that shimmered with the essence of creativity, and a Shocked open mouth  mouth that resonated with the voices of countless creators. On this journey, Pwnky's Comic ear ears fluttered in the electronic winds, and Cool blue hair hair flowed like the rivers of code that shaped the landscape. Adorned with a Black hat hat crafted by the artisans of the net, Pwnky discovered the Horns, a relic that could unlock new realms in this infinite universe.",
    "dimensions": "370x370",
    "hash": "4474_2024-04-11_233532",
    "description": "a new Pwnkey with Cyan, Blue eyes , Zombie, Shocked open mouth , Comic ear, Cool blue hair, Black hat, Horns",
    "rarity_percentages": {
        "Cyan.png": "6.26%",
        "Blue eyes .png": "7.10%",
        "Zombie.png": "19.45%",
        "Shocked open mouth .png": "13.88%",
        "Comic ear.png": "14.02%",
        "Cool blue hair.png": "7.40%",
        "Black hat.png": "12.77%",
        "Horns.png": "14.20%"
    },
    "rarity": "Common"
}