{
    "collection": "Pwnkey",
    "id": 811,
    "assets": [
        "Red .png",
        "Light blue eyes .png",
        "Sick.png",
        "Mechanic mouth .png",
        "Gold earrings .png",
        "Golden hair.png",
        "Crown.png",
        "Horns.png"
    ],
    "creation_time": "2024-04-11 23:30:13",
    "story": "Pwnky, a creature from the Red  of Inpinity Online, ventured through the digital realms with Light blue eyes  eyes that sparkled with curiosity, a Sick body that shimmered with the essence of creativity, and a Mechanic mouth  mouth that resonated with the voices of countless creators. On this journey, Pwnky's Gold earrings  ears fluttered in the electronic winds, and Golden hair hair flowed like the rivers of code that shaped the landscape. Adorned with a Crown hat crafted by the artisans of the net, Pwnky discovered the Horns, a relic that could unlock new realms in this infinite universe.",
    "dimensions": "370x370",
    "hash": "811_2024-04-11_233013",
    "description": "a new Pwnkey with Red , Light blue eyes , Sick, Mechanic mouth , Gold earrings , Golden hair, Crown, Horns",
    "rarity_percentages": {
        "Red .png": "5.99%",
        "Light blue eyes .png": "6.79%",
        "Sick.png": "20.73%",
        "Mechanic mouth .png": "14.74%",
        "Gold earrings .png": "13.97%",
        "Golden hair.png": "14.62%",
        "Crown.png": "12.51%",
        "Horns.png": "14.20%"
    },
    "rarity": "Common"
}