{
    "collection": "Pwnkey",
    "id": 5702,
    "assets": [
        "Yellow Clouds.png",
        "Brown eyes .png",
        "Golden body.png",
        "Hilarious laughing .png",
        "Ears Up!.png",
        "Brown hair.png",
        "Astronaut suite .png",
        "Jacket .png"
    ],
    "creation_time": "2024-04-11 23:37:25",
    "story": "Pwnky, a creature from the Yellow Clouds of Inpinity Online, ventured through the digital realms with Brown eyes  eyes that sparkled with curiosity, a Golden body body that shimmered with the essence of creativity, and a Hilarious laughing  mouth that resonated with the voices of countless creators. On this journey, Pwnky's Ears Up! ears fluttered in the electronic winds, and Brown hair hair flowed like the rivers of code that shaped the landscape. Adorned with a Astronaut suite  hat crafted by the artisans of the net, Pwnky discovered the Jacket , a relic that could unlock new realms in this infinite universe.",
    "dimensions": "370x370",
    "hash": "5702_2024-04-11_233725",
    "description": "a new Pwnkey with Yellow Clouds, Brown eyes , Golden body, Hilarious laughing , Ears Up!, Brown hair, Astronaut suite , Jacket ",
    "rarity_percentages": {
        "Yellow Clouds.png": "6.11%",
        "Brown eyes .png": "6.95%",
        "Golden body.png": "20.32%",
        "Hilarious laughing .png": "13.52%",
        "Ears Up!.png": "14.30%",
        "Brown hair.png": "7.04%",
        "Astronaut suite .png": "12.23%",
        "Jacket .png": "14.68%"
    },
    "rarity": "Epic"
}